Metadata-Version: 2.1
Name: Winerygpt
Version: 0.0.1
Summary: Winery CahtGPT
Author: Janvi Mehta
Author-email: <jmehta@sigmasolve.net>
Keywords: python
Classifier: Development Status :: 1 - Planning
Classifier: Intended Audience :: Developers
Classifier: Programming Language :: Python :: 3
Classifier: Operating System :: Unix
Classifier: Operating System :: MacOS :: MacOS X
Classifier: Operating System :: Microsoft :: Windows
